nat/meta/pypi.md
nat/plugins/opentelemetry/__init__.py
nat/plugins/opentelemetry/otel_span.py
nat/plugins/opentelemetry/otel_span_exporter.py
nat/plugins/opentelemetry/otlp_span_adapter_exporter.py
nat/plugins/opentelemetry/otlp_span_redaction_adapter_exporter.py
nat/plugins/opentelemetry/register.py
nat/plugins/opentelemetry/span_converter.py
nat/plugins/opentelemetry/mixin/__init__.py
nat/plugins/opentelemetry/mixin/otlp_span_exporter_mixin.py
nvidia_nat_opentelemetry-1.3.1.dist-info/licenses/LICENSE-3rd-party.txt
nvidia_nat_opentelemetry-1.3.1.dist-info/licenses/LICENSE.md
nvidia_nat_opentelemetry-1.3.1.dist-info/METADATA
nvidia_nat_opentelemetry-1.3.1.dist-info/WHEEL
nvidia_nat_opentelemetry-1.3.1.dist-info/entry_points.txt
nvidia_nat_opentelemetry-1.3.1.dist-info/top_level.txt
nvidia_nat_opentelemetry-1.3.1.dist-info/RECORD
