Metadata-Version: 2.4
Name: nvidia-nat-opentelemetry
Version: 1.3.1
Summary: Subpackage for OpenTelemetry integration in NeMo Agent toolkit
Author: NVIDIA Corporation
Maintainer: NVIDIA Corporation
License: Apache-2.0
Project-URL: documentation, https://docs.nvidia.com/nemo/agent-toolkit/latest/
Project-URL: source, https://github.com/NVIDIA/NeMo-Agent-Toolkit
Keywords: ai,observability,opentelemetry
Classifier: Programming Language :: Python
Classifier: Programming Language :: Python :: 3.11
Classifier: Programming Language :: Python :: 3.12
Classifier: Programming Language :: Python :: 3.13
Requires-Python: <3.14,>=3.11
License-File: LICENSE-3rd-party.txt
License-File: LICENSE.md
Requires-Dist: nvidia-nat==v1.3.1
Requires-Dist: opentelemetry-api~=1.2
Requires-Dist: opentelemetry-exporter-otlp~=1.3
Requires-Dist: opentelemetry-sdk~=1.3
Dynamic: license-file
